[
  {
    "fullData": "{\"id\":1,\"label\":{\"labelName\":\"이름\",\"labelEmail\":\"Email.\",\"labelPhone\":\"Tel.\",\"labelFax\":\"Fax.\",\"labelCompany\":\"회사명\",\"labelPosition\":\"직책\",\"labelTeam\":\"부서\",\"labelComNum\":\"Company Tel.\",\"labelComAddr\":\"회사주소\",\"style\":{\"email\":{\"fontSize\":2.5,\"fontFamily\":\"sd_gothic_m\",\"color\":\"#6270EA\",\"left\":\"59%\",\"top\":\"59%\",\"position\":\"absolute\",\"fontWeight\":\"bold\"},\"phone\":{\"fontSize\":2.5,\"fontFamily\":\"sd_gothic_m\",\"color\":\"#6270EA\",\"left\":\"31%\",\"top\":\"59%\",\"position\":\"absolute\",\"fontWeight\":\"bold\"},\"fax\":{\"fontSize\":2.5,\"fontFamily\":\"sd_gothic_m\",\"color\":\"#6270EA\",\"left\":\"75%\",\"top\":\"65%\",\"position\":\"absolute\",\"fontWeight\":\"bold\"},\"comNum\":{\"fontSize\":2.5,\"fontFamily\":\"sd_gothic_m\",\"color\":\"#6270EA\",\"left\":\"31%\",\"top\":\"65%\",\"fontWeight\":\"bold\",\"position\":\"absolute\"}}},\"value\":{\"ca",
    "fullData2": "rdName\":\"card1\",\"valueName\":\"hyeonwoo\",\"valueEmail\":\"\",\"valuePhone\":\"1234123412\",\"valueFax\":\"\",\"valueCompany\":\"\",\"valuePosition\":\"\",\"valueTeam\":\"\",\"valueComNum\":\"\",\"valueComAddr\":\"서울 강남구 테헤란로 113 목화밀라드 301호\",\"background\":{\"isColor\":true,\"color\":\"#cdcdcd\"},\"style\":{\"name\":{\"left\":\"43%\",\"top\":\"39%\",\"fontSize\":5,\"fontFamily\":\"sd_gothic_m\",\"fontWeight\":\"bold\",\"color\":\"black\",\"letterSpacing\":3,\"position\":\"absolute\"},\"email\":{\"fontSize\":2.5,\"fontFamily\":\"sd_gothic_m\",\"color\":\"#333333\",\"left\":\"68%\",\"top\":\"59%\",\"fontWeight\":\"bold\",\"position\":\"absolute\"},\"phone\":{\"fontSize\":2.5,\"fontFamily\":\"sd_gothic_m\",\"color\":\"#333333\",\"left\":\"37%\",\"top\":\"59%\",\"fontWeight\":\"bold\",\"position\":\"absolute\"},\"fax\":{\"fontSize\":2.5,\"fontFamily\":\"sd_gothic_m\",\"color\":\"#333333\",\"left\":\"80%\",\"top\"",
    "fullData3": ":\"65%\",\"fontWeight\":\"bold\",\"position\":\"absolute\"},\"company\":{\"fontSize\":4,\"fontFamily\":\"sd_gothic_m\",\"color\":\"#333333\",\"left\":\"0%\",\"top\":\"0%\",\"position\":\"absolute\"},\"position\":{\"fontSize\":2.5,\"fontFamily\":\"sd_gothic_m\",\"color\":\"#6270EA\",\"left\":\"31%\",\"top\":\"43%\",\"fontWeight\":\"bold\",\"position\":\"absolute\"},\"team\":{\"fontSize\":4,\"fontFamily\":\"sd_gothic_m\",\"color\":\"#333333\",\"left\":\"0%\",\"top\":\"0%\",\"position\":\"absolute\"},\"comNum\":{\"fontSize\":2.5,\"fontFamily\":\"sd_gothic_m\",\"color\":\"#333333\",\"left\":\"47%\",\"top\":\"65%\",\"fontWeight\":\"bold\",\"position\":\"absolute\"},\"comAddr\":{\"fontSize\":2.5,\"fontFamily\":\"sd_gothic_m\",\"color\":\"#333333\",\"left\":\"31%\",\"top\":\"53%\",\"fontWeight\":\"bold\",\"position\":\"absolute\"},\"logo\":{\"width\":20,\"height\":20,\"left\":\"10%\",\"top\":\"38%\",\"position\":\"absolute\"}}}}",
    "id": 1
  }
]
